Workbook

Sheet BOQ
D1: QUOTATION
D4: Doc No. 文件号: | E4: QUO/PTJMTI/BBS/PRSG/4/26/R127
D5: Date日期: | E5: =NOW() -> 46206.708
D7: Payment Terms 付款条件:
D8: DP - 40% after signing contract
D9: 预付款 - 合同签署后支付 40%
A10: To: | B10: PT. JIANGYI MOLD TECHNOLOGY INDONESIA | D10: Payment 1: 30% after 60% work progress
B11: Bangsri Utara, Bangsri, Kec. Bulakamba, Kabupaten Brebes, | D11: 第一期付款：支付 30% 工程进度60%
B12: Jawa Tengah 52253 | D12: Payment 2: 25% after 100% work progress
A13: Attn: | D13: 第二期付款：支付 25%工程进度100%
A14: Tel: | D14: Retention: 5% after BAST
D15: 质保金：项目验收（BAST）后支付 5%
A16: Project项目: PEMBUATAN RUANG SELASAR GEDUNG PRODUKSI 生产车间连廊空间建设
A18: No. 号 | B18: Description 工作项目 | C18: Qty 数量 | D18: Unit 单位 | E18: Harga Satuan 单价 | F18: Jumlah Harga 总价 | G18: Brand Spek 品牌规格
E19: (Rp) | F19: (Rp)
A20: A | B20: PEKERJAAN PERSIAPAN 施工准备工作
A21: 1 | B21: Mob dan Demobilisasi 设备和人员的进出场 | C21: =VOL!W11 -> 1 | D21: =VOL!X11 -> ls | E21: 2000000 | F21: =C21*E21 -> 2000000
A22: 2 | B22: Alat Bantu Pekerjaan 施工辅助工具 | C22: =VOL!W12 -> 1 | D22: =VOL!X12 -> ls | E22: 1000000 | F22: =C22*E22 -> 1000000
A23: 3 | B23: Safety | C23: =VOL!W13 -> 1 | D23: =VOL!X13 -> ls | E23: 500000 | F23: =C23*E23 -> 500000
A24: 4 | B24: Cleaning 清理 | C24: =VOL!W14 -> 1 | D24: =VOL!X14 -> ls | E24: 500000 | F24: =C24*E24 -> 500000
A26: B | B26: RUANG SELASAR GEDUNG PRODUKSI (A & B) A栋及B栋生产车间走廊区域
A27: 1 | B27: Pekerjaan Partisi UPVC 隔断工程 | C27: =VOL!W17 -> 203.44275 | D27: =VOL!X17 -> m2 | E27: 410000 | F27: =C27*E27 -> 83411528
B28: Spek :
A29: - | B29: Partisi UPVC Single Layer 单层UPVC隔断 | G29: Alderon/Setara
A30: - | B30: Siku 50x50mm 角钢 | G30: KS/LS/Setara
A31: - | B31: CNP 100x50x2,3mm C型钢 | G31: KS/LS/Setara
A32: - | B32: Pengecatan Rangka Partisi 隔断骨架油漆施工 | G32: Ftalit - Kansai
A34: 2 | B34: Pekerjaan Cor Lantai 地面混凝土浇筑工程
B35: scoope :
A36: - | B36: Plastik Cor 混凝土保护塑料膜 | C36: =VOL!W34 -> 127.88315 | D36: =VOL!X34 -> m2 | E36: 4500 | F36: =C36*E36 -> 575474.18
A37: - | B37: Wiremesh M8, 2 Lapis 钢筋网片 | C37: =VOL!W39 -> 255.7663 | D37: =VOL!X39 -> m2 | E37: 107073.26 | F37: =C37*E37 -> 27385731 | G37: KS/LS/Setara
A38: - | B38: Bekisting 模板 | C38: =VOL!W41 -> 27.408 | D38: =VOL!X41 -> m2 | E38: 150000 | F38: =C38*E38 -> 4111200 | G38: Multipleks
A39: - | B39: Beton K-350 混凝土 | C39: =VOL!W45 -> 38.796945 | D39: =VOL!X45 -> m3 | E39: 1300000 | F39: =C39*E39 -> 50436028 | G39: Ready Mix
A41: 3 | B41: Pintu Double Swing uk. 2200x4000mm 双开门 | C41: =VOL!W49 -> 2 | D41: =VOL!X49 -> unit | E41: 9650000 | F41: =C41*E41 -> 19300000
B42: Spek :
A43: - | B43: Kusen Hollow 100x100x3mm 门框采用100x100x3mm方管 | G43: KS/LS/Setara
A44: - | B44: Siku 50x50x5mm 角钢 | G44: KS/LS/Setara
A45: - | B45: Partisi UPVC Single Layer 单层UPVC隔断 | G45: Alderon/Setara
A46: - | B46: Finishing Cat Besi 钢结构油漆饰面 | G46: Ftalit - Kansai
A47: - | B47: Aksesoris 门配件
A49: 4 | B49: Jendela Sliding (J1), uk. 144x140 cm J1型推拉窗，尺寸144×140cm | C49: =VOL!W57 -> 2 | D49: =VOL!X57 -> unit | E49: 2200000 | F49: =C49*E49 -> 4400000
B50: Spek :
A51: - | B51: Daun Pintu Aluminium 4" 铝合金窗扇 | G51: Dacon/Mulia/setara
A52: - | B52: Kaca Polos 5mm 5mm透明玻璃 | G52: Mulia/setara
A53: - | B53: Aksesoris 配件 | G53: Dekson/setara
A55: 5 | B55: Tutup Manhole uk. 600x600mm 检查井盖板，尺寸600x600mm | C55: =VOL!W63 -> 4 | D55: =VOL!X63 -> unit | E55: 590000 | F55: =C55*E55 -> 2360000
B56: Spek :
A57: - | B57: Siku 50x50x5mm 角钢 | G57: KS/LS/Setara
A58: - | B58: Plat Bordes 4,5mm 4.5mm花纹钢板 | G58: KS/LS/Setara
A59: - | B59: Finishing Cat Besi 钢结构油漆饰面 | G59: Ftalit - Kansai
A61: 6 | B61: Tanggulan 10cm 高挡土埂 | C61: =VOL!W68 -> 5.2 | D61: =VOL!X68 -> m | E61: 125000 | F61: =C61*E61 -> 650000
B63: *Note : Pekerjaan 2 Unit Ruang Selasar 两间连廊空间施工
A65: C | B65: PENAMBAHAN SEKAT DINDING, PINTU DAN JENDELA KANTIN KARYAWAN 员工食堂隔墙、门窗增设工程
A66: 1 | B66: Bongkaran Dinding Existing 现有墙体拆除工程 | C66: =VOL!W74 -> 1.68 | D66: =VOL!X74 -> m2 | E66: 45000 | F66: =C66*E66 -> 75600
A67: 2 | B67: Perapihan Dinding 墙面修复及整理工程 | C67: =VOL!W75 -> 5.2 | D67: =VOL!X75 -> m | E67: 35000 | F67: =C67*E67 -> 182000
A68: 3 | B68: Dinding Bata Ringan 轻质砖墙 | C68: =VOL!W76 -> 10.676 | D68: =VOL!X76 -> m2 | E68: 115000 | F68: =C68*E68 -> 1227740
A69: 4 | B69: Plesteran & Acian Dinding 墙面抹灰及找平 | C69: =VOL!W81 -> 21.352 | D69: =VOL!X81 -> m2 | E69: 110000 | F69: =C69*E69 -> 2348720
A70: 5 | B70: Finishing Cat Dinding 墙面油漆饰面 | C70: =VOL!W82 -> 21.352 | D70: =VOL!X82 -> m2 | E70: 36000 | F70: =C70*E70 -> 768672 | G70: Vinilex/Setara
A71: 6 | B71: Kolom & Balok Praktis 构造柱及圈梁 | C71: =VOL!W83 -> 3.7 | D71: =VOL!X83 -> m | E71: 145000 | F71: =C71*E71 -> 536500
A72: 7 | B72: Pintu Single Swing uk. 100x220cm 单开平开门 尺寸100×220厘米 | C72: =VOL!W84 -> 1 | D72: =VOL!X84 -> unit | E72: 4160000 | F72: =C72*E72 -> 4160000
B73: Spek :
A74: - | B74: Kusen Aluminium 4" Warna Putih 铝合金框 | G74: Dacon/Mulia/setara
A75: - | B75: Kaca Rayban Hitam | G75: Mulia/setara
A76: - | B76: Aksesoris 配件 | G76: Dekson/setara
A78: 8 | B78: Jendela Sliding (J1), uk. 144x120 cm J1型推拉窗，尺寸144×120cm | C78: =VOL!W92 -> 1 | D78: =VOL!X92 -> unit | E78: 2200000 | F78: =C78*E78 -> 2200000
B79: Spek :
A80: - | B80: Daun Pintu Aluminium 4" 铝合金窗扇 | G80: Dacon/Mulia/setara
A81: - | B81: Kaca Polos 5mm 5mm透明玻璃 | G81: Mulia/setara
A82: - | B82: Aksesoris 配件 | G82: Dekson/setara
B84: SUBTOTAL 小计 | F84: =SUM(F20:F83) -> 2.0812919e+08
D86: TOTAL 合计 | E86: =F84 -> 2.0812919e+08
A87: Bank Account 银行账号: | D87: DISCOUNT 折扣
A88: Bank BCA | D88: GRAND TOTAL 总计 | E88: =E86+E87 -> 2.0812919e+08
A89: No. Rek: 460-447-4444
A90: PT. Modern Jaya Konstruksi
A92: NOTE:
A93: 1. The price stated above included (eg: installation, transportation fees etc.) 以上所述价格包括（例如：安装费，运输费等）
A94: 2. The price stated above not included PPN 11% and include PPH 以上所述价格不包括11%的增值税，并包括个人所得税。
A96: We hope you find our quotation favorable and kindly confirm your acceptance by signing this document:
A97: 我们希望您对我们的报价感到满意，并请通过签署此文件确认您的接受。
A104: Name 名字 : | D104: Name 名字 :
A105: =B10 -> PT. JIANGYI MOLD TECHNOLOGY INDONESIA | D105: PT. MODERN JAYA KONSTRUKSI
A106: Date 日期: | D106: Date 日期:

Sheet VOL
B1: PT. MJK
B2: =BOQ!A16 -> Project项目: PEMBUATAN RUANG SELASAR GEDUNG PRODUKSI 生产车间连廊空间建设
B3: Back Up Volume
B6: No | C6: Uraian Pekerjaan | H6: Dia. | I6: Formation Of Bar Member | Q6: Dimensi | V6: n | W6: Volume | X6: Sat
I7: 1.5 | J7: 4 | K7: 6 | L7: 12 | M7: 15 | N7: 25 | O7: 40 | P7: 50 | Q7: Panjang | R7: Lebar | S7: tinggi | T7: Kg(m) | U7: qty
Q8: (m) | R8: (m) | S8: (m)
B10: =BOQ!A20 -> A | C10: =BOQ!B20 -> PEKERJAAN PERSIAPAN 施工准备工作
B11: =BOQ!A21 -> 1 | C11: =BOQ!B21 -> Mob dan Demobilisasi 设备和人员的进出场 | W11: 1 | X11: ls
B12: =BOQ!A22 -> 2 | C12: =BOQ!B22 -> Alat Bantu Pekerjaan 施工辅助工具 | W12: 1 | X12: ls
B13: =BOQ!A23 -> 3 | C13: =BOQ!B23 -> Safety | W13: 1 | X13: ls
B14: =BOQ!A24 -> 4 | C14: =BOQ!B24 -> Cleaning 清理 | W14: 1 | X14: ls
B15: =BOQ!A25 -> 0 | C15: =BOQ!B25 -> 0
B16: =BOQ!A26 -> B | C16: =BOQ!B26 -> RUANG SELASAR GEDUNG PRODUKSI (A & B) A栋及B栋生产车间走廊区域
B17: =BOQ!A27 -> 1 | C17: =BOQ!B27 -> Pekerjaan Partisi UPVC 隔断工程 | W17: =SUM(W23:W30) -> 203.44275 | X17: m2 | Y17: =W17*3% -> 6.1032825 | Z17: =W17-Y17 -> 197.33947
C18: =BOQ!B28 -> Spek :
B19: =BOQ!A29 -> - | C19: =BOQ!B29 -> Partisi UPVC Single Layer 单层UPVC隔断
B20: =BOQ!A30 -> - | C20: =BOQ!B30 -> Siku 50x50mm 角钢
B21: =BOQ!A31 -> - | C21: =BOQ!B31 -> CNP 100x50x2,3mm C型钢
B22: =BOQ!A32 -> - | C22: =BOQ!B32 -> Pengecatan Rangka Partisi 隔断骨架油漆施工
G23: gedung A | H23: tampak depan | Q23: 12.43 | S23: 4.825 | U23: 1 | W23: =Q23*S23*U23 -> 59.97475
H24: tampak samping | Q24: 5.18 | S24: =(5.275+4.825)/2 -> 5.05 | U24: 1 | W24: =Q24*S24*U24 -> 26.159
Q25: 5.23 | S25: =(5.275+4.825)/2 -> 5.05 | U25: 1 | W25: =Q25*S25*U25 -> 26.4115
G26: gedung B | H26: tampak depan | Q26: 12.5 | S26: 4.825 | U26: 1 | W26: =Q26*S26*U26 -> 60.3125
H27: tampak samping | Q27: 5.2 | S27: =(5.275+4.825)/2 -> 5.05 | U27: 1 | W27: =Q27*S27*U27 -> 26.26
Q28: 5.14 | S28: =(5.275+4.825)/2 -> 5.05 | U28: 1 | W28: =Q28*S28*U28 -> 25.957
H29: pengurangan pintu | Q29: 2.2 | S29: 4 | U29: =-W49 -> -2 | W29: =Q29*S29*U29 -> -17.6
H30: jendela | Q30: 1.44 | S30: 1.4 | U30: =-W57 -> -2 | W30: =Q30*S30*U30 -> -4.032
B32: =BOQ!A34 -> 2 | C32: =BOQ!B34 -> Pekerjaan Cor Lantai 地面混凝土浇筑工程
B33: =BOQ!A35 -> 0 | C33: =BOQ!B35 -> scoope :
B34: =BOQ!A36 -> - | C34: =BOQ!B36 -> Plastik Cor 混凝土保护塑料膜 | W34: =SUM(W35:W38) -> 127.88315 | X34: m2 | Y34: =W34*3% -> 3.8364945 | Z34: =W34-Y34 -> 124.04666
Q35: =Q23 -> 12.43 | S35: =(5.18+5.23)/2 -> 5.205 | U35: 1 | W35: =Q35*S35*U35 -> 64.69815
Q36: =Q26 -> 12.5 | S36: =(5.2+5.14)/2 -> 5.17 | U36: 1 | W36: =Q36*S36*U36 -> 64.625
H37: Tutup manhole | Q37: 0.6 | S37: 0.6 | U37: 2 | V37: -2 | W37: =Q37*S37*U37*V37 -> -1.44
B39: =BOQ!A37 -> - | C39: =BOQ!B37 -> Wiremesh M8, 2 Lapis 钢筋网片 | W39: =W34*2 -> 255.7663 | X39: m2 | Y39: =W39*3% -> 7.672989 | Z39: =W39-Y39 -> 248.09331
B41: =BOQ!A38 -> - | C41: =BOQ!B38 -> Bekisting 模板 | U41: 2 | W41: =SUM(W42:W44) -> 27.408 | X41: m2 | Y41: =W41*3% -> 0.82224 | Z41: =W41-Y41 -> 26.58576
Q42: =Q46+R46*2 -> 22.84 | S42: =S46 -> 0.3 | U42: 2 | W42: =Q42*S42*U42 -> 13.704
Q43: =Q47+R47*2 -> 22.84 | S43: =S42 -> 0.3 | U43: 2 | W43: =Q43*S43*U43 -> 13.704
B45: =BOQ!A39 -> - | C45: =BOQ!B39 -> Beton K-350 混凝土 | W45: =SUM(W46:W48) -> 38.796945 | X45: m3 | Y45: =W45*3% -> 1.1639083 | Z45: =W45-Y45 -> 37.633037
Q46: =Q35 -> 12.43 | R46: =S35 -> 5.205 | S46: 0.3 | U46: 1 | W46: =Q46*R46*S46*U46 -> 19.409445
Q47: =Q36 -> 12.5 | R47: =S36 -> 5.17 | S47: =S46 -> 0.3 | U47: 1 | W47: =Q47*R47*S47*U47 -> 19.3875
B49: =BOQ!A41 -> 3 | C49: =BOQ!B41 -> Pintu Double Swing uk. 2200x4000mm 双开门 | W49: 2 | X49: unit
B50: =BOQ!A42 -> 0 | C50: =BOQ!B42 -> Spek :
B51: =BOQ!A43 -> - | C51: =BOQ!B43 -> Kusen Hollow 100x100x3mm 门框采用100x100x3mm方管
B52: =BOQ!A44 -> - | C52: =BOQ!B44 -> Siku 50x50x5mm 角钢
B53: =BOQ!A45 -> - | C53: =BOQ!B45 -> Partisi UPVC Single Layer 单层UPVC隔断
B54: =BOQ!A46 -> - | C54: =BOQ!B46 -> Finishing Cat Besi 钢结构油漆饰面
B55: =BOQ!A47 -> - | C55: =BOQ!B47 -> Aksesoris 门配件
B57: =BOQ!A49 -> 4 | C57: =BOQ!B49 -> Jendela Sliding (J1), uk. 144x140 cm J1型推拉窗，尺寸144×140cm | W57: 2 | X57: unit
B58: =BOQ!A50 -> 0 | C58: =BOQ!B50 -> Spek :
B59: =BOQ!A51 -> - | C59: =BOQ!B51 -> Daun Pintu Aluminium 4" 铝合金窗扇
B60: =BOQ!A52 -> - | C60: =BOQ!B52 -> Kaca Polos 5mm 5mm透明玻璃
B61: =BOQ!A53 -> - | C61: =BOQ!B53 -> Aksesoris 配件
B63: =BOQ!A55 -> 5 | C63: =BOQ!B55 -> Tutup Manhole uk. 600x600mm 检查井盖板，尺寸600x600mm | U63: 2 | V63: 2 | W63: =U63*V63 -> 4 | X63: unit
B64: =BOQ!A56 -> 0 | C64: =BOQ!B56 -> Spek :
B65: =BOQ!A57 -> - | C65: =BOQ!B57 -> Siku 50x50x5mm 角钢
B66: =BOQ!A58 -> - | C66: =BOQ!B58 -> Plat Bordes 4,5mm 4.5mm花纹钢板
B67: =BOQ!A59 -> - | C67: =BOQ!B59 -> Finishing Cat Besi 钢结构油漆饰面
W68: 5.2 | X68: m
B69: =BOQ!A61 -> 6 | C69: =BOQ!B61 -> Tanggulan 10cm 高挡土埂
B71: =BOQ!A63 -> 0 | C71: =BOQ!B63 -> *Note : Pekerjaan 2 Unit Ruang Selasar 两间连廊空间施工
B73: =BOQ!A65 -> C | C73: =BOQ!B65 -> PENAMBAHAN SEKAT DINDING, PINTU DAN JENDELA KANTIN KARYAWAN 员工食堂隔墙、门窗增设工程
B74: =BOQ!A66 -> 1 | C74: =BOQ!B66 -> Bongkaran Dinding Existing 现有墙体拆除工程 | Q74: 1.4 | R74: 1.2 | V74: 1 | W74: =Q74*R74*V74 -> 1.68 | X74: m2 | Y74: =W74*3% -> 0.0504 | Z74: =W74-Y74 -> 1.6296
B75: =BOQ!A67 -> 2 | C75: =BOQ!B67 -> Perapihan Dinding 墙面修复及整理工程 | Q75: =Q74 -> 1.4 | R75: =R74 -> 1.2 | V75: 2 | W75: =(Q75+R75)*V75 -> 5.2 | X75: m | Y75: =W75*3% -> 0.156 | Z75: =W75-Y75 -> 5.044
B76: =BOQ!A68 -> 3 | C76: =BOQ!B68 -> Dinding Bata Ringan 轻质砖墙 | W76: =SUM(W77:W80) -> 10.676 | X76: m2 | Y76: =W76*3% -> 0.32028 | Z76: =W76-Y76 -> 10.35572
Q77: 1.83 | R77: 3.7 | V77: 1 | W77: =Q77*R77*V77 -> 6.771
Q78: 1.65 | R78: =R77 -> 3.7 | V78: 1 | W78: =Q78*R78*V78 -> 6.105
Q79: 1 | R79: 2.2 | V79: -1 | W79: =Q79*R79*V79 -> -2.2
B81: =BOQ!A69 -> 4 | C81: =BOQ!B69 -> Plesteran & Acian Dinding 墙面抹灰及找平 | W81: =W76*2 -> 21.352 | X81: m2 | Y81: =W81*3% -> 0.64056 | Z81: =W81-Y81 -> 20.71144
B82: =BOQ!A70 -> 5 | C82: =BOQ!B70 -> Finishing Cat Dinding 墙面油漆饰面 | W82: =W81 -> 21.352 | X82: m2 | Y82: =W82*3% -> 0.64056 | Z82: =W82-Y82 -> 20.71144
B83: =BOQ!A71 -> 6 | C83: =BOQ!B71 -> Kolom & Balok Praktis 构造柱及圈梁 | S83: =R77 -> 3.7 | V83: 1 | W83: =S83*V83 -> 3.7 | X83: m | Y83: =W83*3% -> 0.111 | Z83: =W83-Y83 -> 3.589
B84: =BOQ!A72 -> 7 | C84: =BOQ!B72 -> Pintu Single Swing uk. 100x220cm 单开平开门 尺寸100×220厘米 | W84: 1 | X84: unit
B85: =BOQ!A73 -> 0 | C85: =BOQ!B73 -> Spek :
B86: =BOQ!A74 -> - | C86: =BOQ!B74 -> Kusen Aluminium 4" Warna Putih 铝合金框
B87: =BOQ!A75 -> - | C87: =BOQ!B75 -> Kaca Rayban Hitam
B88: =BOQ!A76 -> - | C88: =BOQ!B76 -> Aksesoris 配件
B90: =BOQ!A78 -> 8 | C90: =BOQ!B78 -> Jendela Sliding (J1), uk. 144x120 cm J1型推拉窗，尺寸144×120cm
B91: =BOQ!A79 -> 0 | C91: =BOQ!B79 -> Spek :
B92: =BOQ!A80 -> - | C92: =BOQ!B80 -> Daun Pintu Aluminium 4" 铝合金窗扇 | W92: 1 | X92: unit
B93: =BOQ!A81 -> - | C93: =BOQ!B81 -> Kaca Polos 5mm 5mm透明玻璃
B94: =BOQ!A82 -> - | C94: =BOQ!B82 -> Aksesoris 配件
